MANIFEST.in
README.md
setup.py
traceutils2/__init__.py
traceutils2/version.py
traceutils2.egg-info/PKG-INFO
traceutils2.egg-info/SOURCES.txt
traceutils2.egg-info/dependency_links.txt
traceutils2.egg-info/entry_points.txt
traceutils2.egg-info/not-zip-safe
traceutils2.egg-info/requires.txt
traceutils2.egg-info/top_level.txt
traceutils2/alias/__init__.py
traceutils2/alias/alias.py
traceutils2/as2org/__init__.py
traceutils2/as2org/as2org.c
traceutils2/as2org/as2org.pxd
traceutils2/as2org/as2org.pyx
traceutils2/bgp/__init__.py
traceutils2/bgp/bgp.c
traceutils2/bgp/bgp.pxd
traceutils2/bgp/bgp.pyx
traceutils2/ixps/__init__.py
traceutils2/ixps/caida.py
traceutils2/ixps/ixps.py
traceutils2/ixps/peeringdb.py
traceutils2/ixps/peeringdb_base.py
traceutils2/ixps/peeringdb_v1.py
traceutils2/radix/__init__.py
traceutils2/radix/ip2as.c
traceutils2/radix/ip2as.pxd
traceutils2/radix/ip2as.pyx
traceutils2/radix/ip2ases.c
traceutils2/radix/ip2ases.pxd
traceutils2/radix/ip2ases.pyx
traceutils2/radix/ip2data.c
traceutils2/radix/ip2data.pxd
traceutils2/radix/ip2data.pyx
traceutils2/radix/radix.c
traceutils2/radix/radix.pxd
traceutils2/radix/radix.pyx
traceutils2/radix/radix_node.c
traceutils2/radix/radix_node.pxd
traceutils2/radix/radix_node.pyx
traceutils2/radix/radix_prefix.c
traceutils2/radix/radix_prefix.pxd
traceutils2/radix/radix_prefix.pyx
traceutils2/radix/radix_tree.c
traceutils2/radix/radix_tree.pxd
traceutils2/radix/radix_tree.pyx
traceutils2/scamper/__init__.py
traceutils2/scamper/atlas.c
traceutils2/scamper/atlas.pxd
traceutils2/scamper/atlas.pyx
traceutils2/scamper/atlas03.pyx
traceutils2/scamper/atlas2.pxd
traceutils2/scamper/hop.c
traceutils2/scamper/hop.pxd
traceutils2/scamper/hop.pyx
traceutils2/scamper/py_atlas.c
traceutils2/scamper/py_atlas.py
traceutils2/scamper/utils.c
traceutils2/scamper/utils.pxd
traceutils2/scamper/utils.pyx
traceutils2/scamper/warts.c
traceutils2/scamper/warts.pxd
traceutils2/scamper/warts.pyx
traceutils2/scripts/__init__.py
traceutils2/scripts/tu_addrs.py
traceutils2/scripts/tu_adjs.py
traceutils2/scripts/tu_pydig.py
traceutils2/utils/__init__.py
traceutils2/utils/dicts.c
traceutils2/utils/dicts.pxd
traceutils2/utils/dicts.pyx
traceutils2/utils/net.c
traceutils2/utils/net.pxd
