Metadata-Version: 2.1
Name: traceutils2
Version: 1.1.20220919155725
Summary: Various packages for traceroute analysis.
Home-page: https://gitlab.com/alexander_marder/traceutils2
Author: Alex Marder
Requires-Python: >3.6
